synergyvue/__init__.py
synergyvue/synergyvue.py
synergyvue-0.0.3.dist-info/LICENSE.md
synergyvue-0.0.3.dist-info/METADATA
synergyvue-0.0.3.dist-info/WHEEL
synergyvue-0.0.3.dist-info/top_level.txt
synergyvue-0.0.3.dist-info/RECORD
