Metadata-Version: 2.1
Name: synergyvue
Version: 0.0.3
Summary: Interface for accessing SynergyVUE data
Home-page: https://github.com/chadcb/synergyvue
Author: Chad Beattie
Author-email: chad@beattie.bz
License: MIT License
Platform: UNKNOWN
Classifier: Programming Language :: Python :: 3
Classifier: License :: OSI Approved :: MIT License
Classifier: Operating System :: OS Independent
Requires-Python: >=3.7
Requires-Dist: zeep (>=3.4.0)
